scriptgenpy/__init__.py
scriptgenpy/scriptgen.py
scriptgenpy-1.0.0.dist-info/LICENSE
scriptgenpy-1.0.0.dist-info/METADATA
scriptgenpy-1.0.0.dist-info/WHEEL
scriptgenpy-1.0.0.dist-info/entry_points.txt
scriptgenpy-1.0.0.dist-info/top_level.txt
scriptgenpy-1.0.0.dist-info/RECORD
