Metadata-Version: 2.1
Name: scriptgenpy
Version: 1.0.0
Summary: ScriptGenPy is a script generator tool that simplifies the process of running scripts in any language.
Author-email: Abhishek Kumar <akbittu@gmail.com>
Maintainer-email: Abhishek Kumar <akbittu@gmail.com>
License: MIT License
Project-URL: Homepage, https://github.com/isurfer21/scriptgen_py
Project-URL: Bug Reports, https://github.com/isurfer21/scriptgen_py/issues
Project-URL: Funding, https://donate.pypi.org
Project-URL: Say Thanks!, https://saythanks.io/to/isurfer21
Project-URL: Source, https://github.com/isurfer21/scriptgen_py/
Keywords: cli,scriptgen,bash,powershell,bat,windows,macos,linux
Classifier: Development Status :: 4 - Beta
Classifier: Intended Audience :: Developers
Classifier: Topic :: Software Development :: Build Tools
Classifier: License :: OSI Approved :: MIT License
Classifier: Programming Language :: Python :: 3
Classifier: Programming Language :: Python :: 3.7
Classifier: Programming Language :: Python :: 3.8
Classifier: Programming Language :: Python :: 3.9
Classifier: Programming Language :: Python :: 3.10
Classifier: Programming Language :: Python :: 3.11
Classifier: Programming Language :: Python :: 3 :: Only
Requires-Python: >=3.7
License-File: LICENSE
